etc/westeros/conf/global.yaml
etc/westeros/conf/shared.yaml
etc/westeros/data/westeros.data
etc/westeros/robot/westeros.robot
tests/__init__.py
tests/capture_test
tests/workflow_1.py
westeros/__init__.py
westeros/auc/__init__.py
westeros/auc/authentication/__init__.py
westeros/auc/authentication/manager.py
westeros/auc/authentication/login/__init__.py
westeros/auc/authentication/login/auc.py
westeros/auc/authentication/logout/__init__.py
westeros/auc/authentication/logout/auc.py
westeros/auc/browser/__init__.py
westeros/auc/browser/manager.py
westeros/auc/browser/close/__init__.py
westeros/auc/browser/close/auc.py
westeros/auc/browser/open/__init__.py
westeros/auc/browser/open/auc.py
westeros/auc/dashboard/__init__.py
westeros/auc/dashboard/manager.py
westeros/auc/database/__init__.py
westeros/auc/database/manager.py
westeros/auc/infrastructure/__init__.py
westeros/auc/infrastructure/manager.py
westeros/auc/infrastructure/clean_disk/__init__.py
westeros/auc/infrastructure/clean_disk/auc.py
westeros/auc/infrastructure/restart_process/__init__.py
westeros/auc/infrastructure/restart_process/auc.py
westeros/auc/rabbitmq/__init__.py
westeros/auc/rabbitmq/manager.py
westeros/auc/rest/__init__.py
westeros/auc/rest/manager.py
westeros/keywords/__init__.py
westeros/keywords/base_workflow.py
westeros/keywords/browser_workflow.py
westeros/keywords/database_workflow.py
westeros/keywords/rabbitmq_workflow.py
westeros/keywords/rest_workflow.py
westeros/keywords/workflows.py
westeros/utils/__init__.py
westeros/utils/dashboard.py
westeros-2.0.1.data/scripts/westeros
westeros-2.0.1.dist-info/DESCRIPTION.rst
westeros-2.0.1.dist-info/METADATA
westeros-2.0.1.dist-info/RECORD
westeros-2.0.1.dist-info/WHEEL
westeros-2.0.1.dist-info/metadata.json
westeros-2.0.1.dist-info/top_level.txt
