Metadata-Version: 2.0
Name: westeros
Version: 2.0.1
Summary: Test automation framework based on robot framework.
Home-page: https://github.com/crazy-canux/westeros
Author: Canux CHENG
Author-email: canuxcheng@gmail.com
License: GPL
Keywords: test automation robot framework
Platform: any
Classifier: Development Status :: 5 - Production/Stable
Classifier: Environment :: Other Environment
Classifier: Framework :: Robot Framework
Classifier: Intended Audience :: Developers
Classifier: License :: OSI Approved :: GNU General Public License (GPL)
Classifier: Natural Language :: English
Classifier: Operating System :: POSIX
Classifier: Programming Language :: Python
Classifier: Programming Language :: Python :: 2.7
Classifier: Topic :: Software Development :: Quality Assurance
